repvar/__init__.py
repvar/__main__.py
repvar_vamanfredi-0.1.21.dist-info/METADATA
repvar_vamanfredi-0.1.21.dist-info/WHEEL
repvar_vamanfredi-0.1.21.dist-info/entry_points.txt
repvar_vamanfredi-0.1.21.dist-info/licenses/LICENSE
repvar_vamanfredi-0.1.21.dist-info/RECORD
